[{"name": "Bernd Leno", "avgAccBackZonePass": 27.150000000000002, "avgAccChippedPass": 13.478260869565217, "avgAccFwdZonePass": 5.25, "avgAccGoalKicks": 21.699604743083004, "avgAccSweeper": 30.0, "avgAccTrows": 29.83783783783784, "avgAccLaunches": 3.8793103448275863, "AvgAccLongBalls": 7.602739726027398, "AvgAccPasses": 21.675, "TotalAerials": 12.0, "AvgWonAerials": 25.0, "AvgLostAerials": 5.0, "AvgAttemptsConcededInBox": 18.39816933638444, "AvgAttemptsConcededOutBox": 11.60183066361556, "TotalAttemptsConceded": 437.0, "BlockedPass": 1.0, "ChallengeLost": 2.0, "CleanSheets": 7, "OddsCleanSheets": 0.23333333333333334, "CrossesNotClaimed": 2.0, "DiveCatches": 1.0, "DivingSave": 59.0, "EffectiveClearances": 26.0, "AvgEffectiveClearances": 32.30769230769231, "EffectiveHeadClearance": 2.0, "GkSmother": 5.0, "AvgGoalsConcededInBox": 26.923076923076923, "AvgGoalsConcededOutBox": 3.0769230769230766, "AvgGoodHighClaim": 30.0, "AvgKeeperPickUp": 6.866666666666666, "AvgLongPassOwnToOpp": 6.7, "AvgLongPassOwnToOppSuccess": 0.005804311774461029, "AvgLostCorners": 0.7666666666666667, "AvgOpenPlayPass": 16.0, "AvgPenGoalsConceded": 0.2, "AvgPenaltyFaced": 0.23333333333333334, "AvgPenaltySave": 0.14285714285714285, "AvgPossLostAll": 7.633333333333334, "AvgPossLostCtrl": 7.633333333333334, "AvgPossWonDef3rd": 1.2333333333333334, "AvgSavedInbox": 17.256637168141594, "AvgSavedOutbox": 12.477876106194689, "TotalSaves": 113.0, "AvgSaves": 3.7666666666666666, "AvgStandCatch": 0.3333333333333333, "AvgStandSave": 0.11504424778761062, "AvgTouches": 38.93333333333333, "Id": 4985.0, "Team": "Arsenal", "TeamId": 1, "Position": "G"}, {"name": "Emiliano Mart\u00ednez", "avgAccBackZonePass": 3.506849315068493, "avgAccChippedPass": 1.5384615384615385, "avgAccFwdZonePass": 0.8888888888888888, "avgAccGoalKicks": 2.4285714285714284, "avgAccSweeper": null, "avgAccTrows": 3.7333333333333334, "avgAccLaunches": 1.6, "AvgAccLongBalls": 1.3076923076923077, "AvgAccPasses": 2.6422018348623855, "TotalAerials": null, "AvgWonAerials": null, "AvgLostAerials": null, "AvgAttemptsConcededInBox": 2.1621621621621623, "AvgAttemptsConcededOutBox": 1.837837837837838, "TotalAttemptsConceded": 37.0, "CleanSheets": 3, "OddsCleanSheets": 0.75, "DiveCatches": 1.0, "DivingSave": 5.0, "AvgEffectiveClearances": null, "AvgGoalsConcededInBox": 4.0, "AvgGoalsConcededOutBox": null, "AvgGoodHighClaim": 4.0, "AvgKeeperPickUp": 4.75, "AvgLongPassOwnToOpp": 9.0, "AvgLongPassOwnToOppSuccess": 0.05555555555555555, "AvgLostCorners": 0.25, "AvgOpenPlayPass": 17.0, "AvgPenGoalsConceded": null, "AvgPenaltyFaced": null, "AvgPenaltySave": null, "AvgPossLostAll": 9.5, "AvgPossLostCtrl": 9.5, "AvgPossWonDef3rd": 0.5, "AvgSavedInbox": 2.6666666666666665, "AvgSavedOutbox": 1.3333333333333333, "TotalSaves": 9.0, "AvgSaves": 2.25, "AvgStandCatch": null, "AvgStandSave": null, "AvgTouches": 34.5, "Id": 4245.0, "Team": "Arsenal", "TeamId": 1, "Position": "G"}, {"name": "\u00d8rjan Nyland", "avgAccBackZonePass": 6.406779661016949, "avgAccChippedPass": 3.5, "avgAccFwdZonePass": 1.9569892473118278, "avgAccGoalKicks": 2.905660377358491, "avgAccSweeper": null, "avgAccTrows": 6.0344827586206895, "avgAccLaunches": 1.627906976744186, "AvgAccLongBalls": 2.311320754716981, "AvgAccPasses": 3.6842105263157894, "TotalAerials": null, "AvgWonAerials": null, "AvgLostAerials": null, "AvgAttemptsConcededInBox": 3.916666666666667, "AvgAttemptsConcededOutBox": 3.083333333333333, "TotalAttemptsConceded": 84.0, "CleanSheets": 1, "OddsCleanSheets": 0.14285714285714285, "DivingSave": 3.0, "EffectiveClearances": 2.0, "AvgEffectiveClearances": null, "AvgGoalsConcededInBox": 5.833333333333334, "AvgGoalsConcededOutBox": 1.1666666666666665, "AvgGoodHighClaim": 5.25, "AvgKeeperPickUp": 4.714285714285714, "AvgLongPassOwnToOpp": 13.714285714285714, "AvgLongPassOwnToOppSuccess": 0.04017857142857143, "AvgLostCorners": 0.42857142857142855, "AvgOpenPlayPass": 10.714285714285714, "AvgPenGoalsConceded": null, "AvgPenaltyFaced": null, "AvgPenaltySave": null, "AvgPossLostAll": 11.142857142857142, "AvgPossLostCtrl": 11.142857142857142, "AvgPossWonDef3rd": 0.5714285714285714, "AvgSavedInbox": 3.2666666666666666, "AvgSavedOutbox": 3.7333333333333334, "TotalSaves": 15.0, "AvgSaves": 2.142857142857143, "AvgStandCatch": 0.2857142857142857, "AvgStandSave": null, "AvgTouches": 29.142857142857142, "Id": 51416.0, "Team": "Aston Villa", "TeamId": 2, "Position": "G"}, {"name": "Jed Steer", "avgAccBackZonePass": 1.0, "avgAccChippedPass": null, "avgAccFwdZonePass": null, "avgAccGoalKicks": null, "avgAccSweeper": null, "avgAccTrows": null, "avgAccLaunches": null, "AvgAccLongBalls": null, "AvgAccPasses": 0.5, "TotalAerials": null, "AvgWonAerials": null, "AvgLostAerials": null, "AvgAttemptsConcededInBox": null, "AvgAttemptsConcededOutBox": null, "TotalAttemptsConceded": null, "CleanSheets": 0, "OddsCleanSheets": 0.0, "AvgEffectiveClearances": null, "AvgGoalsConcededInBox": null, "AvgGoalsConcededOutBox": null, "AvgGoodHighClaim": null, "AvgKeeperPickUp": null, "AvgLongPassOwnToOpp": 1.0, "AvgLongPassOwnToOppSuccess": null, "AvgLostCorners": null, "AvgOpenPlayPass": 1.0, "AvgPenGoalsConceded": null, "AvgPenaltyFaced": null, "AvgPenaltySave": null, "AvgPossLostAll": 1.0, "AvgPossLostCtrl": 1.0, "AvgPossWonDef3rd": null, "AvgSavedInbox": null, "AvgSavedOutbox": null, "TotalSaves": 0, "AvgSaves": 0.0, "AvgStandCatch": null, "AvgStandSave": null, "AvgTouches": 2.0, "Id": 4348.0, "Team": "Aston Villa", "TeamId": 2, "Position": "G"}, {"name": "Tom Heaton", "avgAccBackZonePass": 17.073170731707318, "avgAccChippedPass": 10.0, "avgAccFwdZonePass": 6.149068322981367, "avgAccGoalKicks": 10.35897435897436, "avgAccSweeper": 20.0, "avgAccTrows": 19.595959595959595, "avgAccLaunches": 5.82010582010582, "AvgAccLongBalls": 6.44808743169399, "AvgAccPasses": 10.398481973434535, "TotalAerials": 7.0, "AvgWonAerials": 20.0, "AvgLostAerials": 0.0, "AvgAttemptsConcededInBox": 13.495934959349594, "AvgAttemptsConcededOutBox": 6.504065040650406, "TotalAttemptsConceded": 369.0, "ChallengeLost": 1.0, "CleanSheets": 4, "OddsCleanSheets": 0.2, "DiveCatches": 1.0, "DivingSave": 30.0, "EffectiveClearances": 12.0, "AvgEffectiveClearances": 21.666666666666664, "EffectiveHeadClearance": 1.0, "GkSmother": 3.0, "AvgGoalsConcededInBox": 17.714285714285715, "AvgGoalsConcededOutBox": 2.2857142857142856, "AvgGoodHighClaim": 18.18181818181818, "AvgKeeperPickUp": 6.9, "AvgLongPassOwnToOpp": 16.1, "AvgLongPassOwnToOppSuccess": 0.015217391304347827, "AvgLostCorners": 0.8, "AvgOpenPlayPass": 12.05, "AvgPenGoalsConceded": 0.15, "AvgPenaltyFaced": 0.15, "AvgPenaltySave": null, "AvgPossLostAll": 12.95, "AvgPossLostCtrl": 12.95, "AvgPossWonDef3rd": 0.35, "AvgSavedInbox": 13.529411764705884, "AvgSavedOutbox": 6.470588235294118, "TotalSaves": 68.0, "AvgSaves": 3.4, "AvgStandCatch": 0.3, "AvgStandSave": 0.058823529411764705, "AvgTouches": 36.7, "Id": 2933.0, "Team": "Aston Villa", "TeamId": 2, "Position": "G"}, {"name": "Pepe Reina", "avgAccBackZonePass": 5.9689922480620154, "avgAccChippedPass": 4.064516129032258, "avgAccFwdZonePass": 2.130434782608696, "avgAccGoalKicks": 5.326086956521739, "avgAccSweeper": 5.833333333333334, "avgAccTrows": 6.805555555555555, "avgAccLaunches": 1.9782608695652173, "AvgAccLongBalls": 2.963963963963964, "AvgAccPasses": 4.6313131313131315, "TotalAerials": null, "AvgWonAerials": null, "AvgLostAerials": null, "AvgAttemptsConcededInBox": 4.688679245283018, "AvgAttemptsConcededOutBox": 2.311320754716981, "TotalAttemptsConceded": 106.0, "ChallengeLost": 2.0, "CleanSheets": 0, "OddsCleanSheets": 0.0, "DivingSave": 15.0, "EffectiveClearances": 10.0, "AvgEffectiveClearances": 7.700000000000001, "EffectiveHeadClearance": 1.0, "GkSmother": 0.0, "AvgGoalsConcededInBox": 6.066666666666666, "AvgGoalsConcededOutBox": 0.9333333333333333, "AvgGoodHighClaim": 4.2, "AvgKeeperPickUp": 6.714285714285714, "AvgLongPassOwnToOpp": 9.857142857142858, "AvgLongPassOwnToOppSuccess": 0.04347826086956522, "AvgLostCorners": 0.42857142857142855, "AvgOpenPlayPass": 15.857142857142858, "AvgPenGoalsConceded": 0.14285714285714285, "AvgPenaltyFaced": 0.2857142857142857, "AvgPenaltySave": 0.5, "AvgPossLostAll": 10.0, "AvgPossLostCtrl": 10.0, "AvgPossWonDef3rd": 1.0, "AvgSavedInbox": 4.48, "AvgSavedOutbox": 2.52, "TotalSaves": 25.0, "AvgSaves": 3.5714285714285716, "AvgStandCatch": 0.2857142857142857, "AvgStandSave": 0.04, "AvgTouches": 40.0, "Id": 2911.0, "Team": "Aston Villa", "TeamId": 2, "Position": "G"}, {"name": "Mark Travers", "avgAccBackZonePass": 0.7777777777777778, "avgAccChippedPass": 0.3333333333333333, "avgAccFwdZonePass": 0.14285714285714285, "avgAccGoalKicks": 0.5714285714285714, "avgAccSweeper": null, "avgAccTrows": 1.0, "avgAccLaunches": null, "AvgAccLongBalls": 0.18181818181818182, "AvgAccPasses": 0.6, "TotalAerials": null, "AvgWonAerials": null, "AvgLostAerials": null, "AvgAttemptsConcededInBox": 0.7222222222222222, "AvgAttemptsConcededOutBox": 0.2777777777777778, "TotalAttemptsConceded": 18.0, "CleanSheets": 0, "OddsCleanSheets": 0.0, "DivingSave": 1.0, "EffectiveClearances": 1.0, "AvgEffectiveClearances": null, "AvgGoalsConcededInBox": 1.0, "AvgGoalsConcededOutBox": null, "AvgGoodHighClaim": null, "AvgKeeperPickUp": 5.0, "AvgLongPassOwnToOpp": 7.0, "AvgLongPassOwnToOppSuccess": 0.14285714285714285, "AvgLostCorners": 1.0, "AvgOpenPlayPass": 17.0, "AvgPenGoalsConceded": null, "AvgPenaltyFaced": null, "AvgPenaltySave": null, "AvgPossLostAll": 10.0, "AvgPossLostCtrl": 10.0, "AvgPossWonDef3rd": 2.0, "AvgSavedInbox": 1.0, "AvgSavedOutbox": null, "TotalSaves": 2.0, "AvgSaves": 2.0, "AvgStandCatch": null, "AvgStandSave": 0.0, "AvgTouches": 33.0, "Id": 50453.0, "Team": "Bournemouth", "TeamId": 127, "Position": "G"}, {"name": "Aaron Ramsdale", "avgAccBackZonePass": 27.68044077134986, "avgAccChippedPass": 12.679245283018869, "avgAccFwdZonePass": 8.979955456570156, "avgAccGoalKicks": 17.05019305019305, "avgAccSweeper": 32.0, "avgAccTrows": 31.63005780346821, "avgAccLaunches": 9.049180327868852, "AvgAccLongBalls": 10.127340823970037, "AvgAccPasses": 17.339901477832512, "TotalAerials": 11.0, "AvgWonAerials": 20.363636363636363, "AvgLostAerials": 11.636363636363637, "AvgAttemptsConcededInBox": 18.78838174273859, "AvgAttemptsConcededOutBox": 13.21161825726141, "TotalAttemptsConceded": 482.0, "BlockedPass": 2.0, "CleanSheets": 4, "OddsCleanSheets": 0.125, "CrossesNotClaimed": 1.0, "DivingSave": 68.0, "EffectiveClearances": 37.0, "AvgEffectiveClearances": null, "GkSmother": 3.0, "AvgGoalsConcededInBox": 27.428571428571427, "AvgGoalsConcededOutBox": 4.571428571428571, "AvgGoodHighClaim": 32.0, "AvgKeeperPickUp": 7.625, "AvgLongPassOwnToOpp": 14.0625, "AvgLongPassOwnToOppSuccess": 0.00875, "AvgLostCorners": 0.96875, "AvgOpenPlayPass": 12.125, "AvgPenGoalsConceded": 0.15625, "AvgPenaltyFaced": 0.15625, "AvgPenaltySave": null, "AvgPossLostAll": 11.78125, "AvgPossLostCtrl": 11.78125, "AvgPossWonDef3rd": 0.4375, "AvgSavedInbox": 17.84070796460177, "AvgSavedOutbox": 13.309734513274336, "TotalSaves": 113.0, "AvgSaves": 3.53125, "AvgStandCatch": 0.125, "AvgStandSave": 0.035398230088495575, "AvgTouches": 36.5625, "Id": 13703.0, "Team": "Bournemouth", "TeamId": 127, "Position": "G"}, {"name": "Mat Ryan", "avgAccBackZonePass": 29.7708830548926, "avgAccChippedPass": 19.907608695652176, "avgAccFwdZonePass": 14.52, "avgAccGoalKicks": 27.934210526315788, "avgAccSweeper": 33.0, "avgAccTrows": 32.413333333333334, "avgAccLaunches": 12.184615384615386, "AvgAccLongBalls": 17.11111111111111, "AvgAccPasses": 26.54280338664158, "TotalAerials": null, "AvgWonAerials": null, "AvgLostAerials": null, "AvgAttemptsConcededInBox": 22.404411764705884, "AvgAttemptsConcededOutBox": 10.595588235294118, "TotalAttemptsConceded": 408.0, "BlockedPass": 4.0, "ChallengeLost": 2.0, "CleanSheets": 8, "OddsCleanSheets": 0.24242424242424243, "CrossesNotClaimed": 1.0, "DivingSave": 38.0, "EffectiveClearances": 17.0, "AvgEffectiveClearances": null, "GkSmother": 7.0, "AvgGoalsConcededInBox": 29.25, "AvgGoalsConcededOutBox": 3.75, "AvgGoodHighClaim": 25.235294117647058, "AvgKeeperPickUp": 8.090909090909092, "AvgLongPassOwnToOpp": 6.818181818181818, "AvgLongPassOwnToOppSuccess": 0.013333333333333334, "AvgLostCorners": 0.5151515151515151, "AvgOpenPlayPass": 22.939393939393938, "AvgPenGoalsConceded": 0.06060606060606061, "AvgPenaltyFaced": 0.06060606060606061, "AvgPenaltySave": 0.0, "AvgPossLostAll": 6.666666666666667, "AvgPossLostCtrl": 6.666666666666667, "AvgPossWonDef3rd": 0.5151515151515151, "AvgSavedInbox": 25.310679611650485, "AvgSavedOutbox": 7.689320388349515, "TotalSaves": 103.0, "AvgSaves": 3.121212121212121, "AvgStandCatch": 0.15151515151515152, "AvgStandSave": 0.13592233009708737, "AvgTouches": 43.878787878787875, "Id": 12192.0, "Team": "Brighton", "TeamId": 131, "Position": "G"}, {"name": "Nick Pope", "avgAccBackZonePass": 25.07142857142857, "avgAccChippedPass": 18.0, "avgAccFwdZonePass": 9.38950276243094, "avgAccGoalKicks": 13.40625, "avgAccSweeper": 31.058823529411764, "avgAccTrows": 32.35714285714286, "avgAccLaunches": 8.839285714285714, "AvgAccLongBalls": 9.958333333333332, "AvgAccPasses": 12.14009111617312, "TotalAerials": 18.0, "AvgWonAerials": 31.166666666666664, "AvgLostAerials": 1.8333333333333333, "AvgAttemptsConcededInBox": 18.969631236442517, "AvgAttemptsConcededOutBox": 14.030368763557483, "TotalAttemptsConceded": 461.0, "BlockedPass": 2.0, "ChallengeLost": 1.0, "CleanSheets": 13, "OddsCleanSheets": 0.393939393939394, "CrossesNotClaimed": 1.0, "DiveCatches": 1.0, "DivingSave": 47.0, "EffectiveClearances": 21.0, "AvgEffectiveClearances": 36.142857142857146, "EffectiveHeadClearance": 2.0, "GkSmother": 3.0, "AvgGoalsConcededInBox": 27.26086956521739, "AvgGoalsConcededOutBox": 5.739130434782608, "AvgGoodHighClaim": 29.16279069767442, "AvgKeeperPickUp": 7.848484848484849, "AvgLongPassOwnToOpp": 22.060606060606062, "AvgLongPassOwnToOppSuccess": 0.008658008658008658, "AvgLostCorners": 0.45454545454545453, "AvgOpenPlayPass": 11.575757575757576, "AvgPenGoalsConceded": 0.12121212121212122, "AvgPenaltyFaced": 0.15151515151515152, "AvgPenaltySave": 0.2, "AvgPossLostAll": 17.12121212121212, "AvgPossLostCtrl": 17.12121212121212, "AvgPossWonDef3rd": 1.0303030303030303, "AvgSavedInbox": 20.46, "AvgSavedOutbox": 11.879999999999999, "TotalSaves": 100.0, "AvgSaves": 3.0303030303030303, "AvgStandCatch": 0.12121212121212122, "AvgStandSave": 0.13, "AvgTouches": 36.90909090909091, "Id": 10079.0, "Team": "Burnley", "TeamId": 43, "Position": "G"}, {"name": "Kepa Arrizabalaga", "avgAccBackZonePass": 26.58698940998487, "avgAccChippedPass": 15.784810126582279, "avgAccFwdZonePass": 8.436363636363636, "avgAccGoalKicks": 22.195530726256983, "avgAccSweeper": 29.0, "avgAccTrows": 28.33076923076923, "avgAccLaunches": 8.419354838709678, "AvgAccLongBalls": 11.6415770609319, "AvgAccPasses": 22.96125907990315, "TotalAerials": null, "AvgWonAerials": null, "AvgLostAerials": null, "AvgAttemptsConcededInBox": 19.411290322580644, "AvgAttemptsConcededOutBox": 9.588709677419354, "TotalAttemptsConceded": 248.0, "BlockedPass": 1.0, "ChallengeLost": 1.0, "CleanSheets": 7, "OddsCleanSheets": 0.2413793103448276, "DivingSave": 32.0, "EffectiveClearances": 10.0, "AvgEffectiveClearances": null, "GkSmother": 4.0, "AvgGoalsConcededInBox": 23.513513513513516, "AvgGoalsConcededOutBox": 5.486486486486487, "AvgGoodHighClaim": 29.0, "AvgKeeperPickUp": 4.655172413793103, "AvgLongPassOwnToOpp": 5.689655172413793, "AvgLongPassOwnToOppSuccess": 0.010031347962382444, "AvgLostCorners": 0.2413793103448276, "AvgOpenPlayPass": 20.517241379310345, "AvgPenGoalsConceded": 0.06896551724137931, "AvgPenaltyFaced": 0.06896551724137931, "AvgPenaltySave": null, "AvgPossLostAll": 6.241379310344827, "AvgPossLostCtrl": 6.241379310344827, "AvgPossWonDef3rd": 1.1379310344827587, "AvgSavedInbox": 17.4, "AvgSavedOutbox": 11.02, "TotalSaves": 50.0, "AvgSaves": 1.7241379310344827, "AvgStandCatch": 0.06896551724137931, "AvgStandSave": 0.06, "AvgTouches": 36.241379310344826, "Id": 11373.0, "Team": "Chelsea", "TeamId": 4, "Position": "G"}, {"name": "Willy Caballero", "avgAccBackZonePass": 3.4074074074074074, "avgAccChippedPass": 2.588235294117647, "avgAccFwdZonePass": 1.1612903225806452, "avgAccGoalKicks": 3.090909090909091, "avgAccSweeper": 4.0, "avgAccTrows": 4.0, "avgAccLaunches": 0.5454545454545454, "AvgAccLongBalls": 1.5272727272727273, "AvgAccPasses": 2.7857142857142856, "TotalAerials": null, "AvgWonAerials": null, "AvgLostAerials": null, "AvgAttemptsConcededInBox": 2.9473684210526314, "AvgAttemptsConcededOutBox": 1.0526315789473684, "TotalAttemptsConceded": 38.0, "CleanSheets": 0, "OddsCleanSheets": 0.0, "DivingSave": 3.0, "EffectiveClearances": 3.0, "AvgEffectiveClearances": null, "AvgGoalsConcededInBox": 4.0, "AvgGoalsConcededOutBox": null, "AvgGoodHighClaim": 4.0, "AvgKeeperPickUp": 4.25, "AvgLongPassOwnToOpp": 7.75, "AvgLongPassOwnToOppSuccess": 0.07258064516129033, "AvgLostCorners": 0.25, "AvgOpenPlayPass": 21.0, "AvgPenGoalsConceded": null, "AvgPenaltyFaced": null, "AvgPenaltySave": null, "AvgPossLostAll": 8.5, "AvgPossLostCtrl": 8.5, "AvgPossWonDef3rd": null, "AvgSavedInbox": 3.111111111111111, "AvgSavedOutbox": 0.8888888888888888, "TotalSaves": 9.0, "AvgSaves": 2.25, "AvgStandCatch": null, "AvgStandSave": 0.1111111111111111, "AvgTouches": 34.5, "Id": 10466.0, "Team": "Chelsea", "TeamId": 4, "Position": "G"}, {"name": "Wayne Hennessey", "avgAccBackZonePass": 1.894736842105263, "avgAccChippedPass": 1.3846153846153846, "avgAccFwdZonePass": 1.1923076923076923, "avgAccGoalKicks": 1.3846153846153846, "avgAccSweeper": 3.0, "avgAccTrows": 3.0, "avgAccLaunches": 1.2000000000000002, "AvgAccLongBalls": 1.1931818181818181, "AvgAccPasses": 1.3298969072164948, "TotalAerials": 1.0, "AvgWonAerials": 0.0, "AvgLostAerials": 3.0, "AvgAttemptsConcededInBox": 2.1578947368421053, "AvgAttemptsConcededOutBox": 0.8421052631578947, "TotalAttemptsConceded": 57.0, "CleanSheets": 0, "OddsCleanSheets": 0.0, "DivingSave": 8.0, "EffectiveClearances": 5.0, "AvgEffectiveClearances": 3.5999999999999996, "EffectiveHeadClearance": 1.0, "AvgGoalsConcededInBox": 2.25, "AvgGoalsConcededOutBox": 0.75, "AvgGoodHighClaim": null, "AvgKeeperPickUp": 5.0, "AvgLongPassOwnToOpp": 26.0, "AvgLongPassOwnToOppSuccess": 0.13247863247863248, "AvgLostCorners": 1.0, "AvgOpenPlayPass": 13.666666666666666, "AvgPenGoalsConceded": null, "AvgPenaltyFaced": null, "AvgPenaltySave": null, "AvgPossLostAll": 18.333333333333332, "AvgPossLostCtrl": 18.333333333333332, "AvgPossWonDef3rd": 0.3333333333333333, "AvgSavedInbox": 1.875, "AvgSavedOutbox": 0.9375, "TotalSaves": 16.0, "AvgSaves": 5.333333333333333, "AvgStandCatch": 0.3333333333333333, "AvgStandSave": 0.0625, "AvgTouches": 42.333333333333336, "Id": 2569.0, "Team": "Crystal Palace", "TeamId": 6, "Position": "G"}, {"name": "Vicente Guaita", "avgAccBackZonePass": 24.78723404255319, "avgAccChippedPass": 11.785714285714285, "avgAccFwdZonePass": 9.375, "avgAccGoalKicks": 13.319502074688796, "avgAccSweeper": 30.0, "avgAccTrows": 29.785714285714285, "avgAccLaunches": 10.227272727272727, "AvgAccLongBalls": 10.17123287671233, "AvgAccPasses": 14.961439588688945, "TotalAerials": 19.0, "AvgWonAerials": 26.842105263157894, "AvgLostAerials": 3.1578947368421053, "AvgAttemptsConcededInBox": 18.939393939393938, "AvgAttemptsConcededOutBox": 11.06060606060606, "TotalAttemptsConceded": 396.0, "CleanSheets": 10, "OddsCleanSheets": 0.3333333333333333, "CrossesNotClaimed": 1.0, "DiveCatches": 3.0, "DivingSave": 43.0, "EffectiveClearances": 37.0, "AvgEffectiveClearances": 31.621621621621617, "EffectiveHeadClearance": 2.0, "GkSmother": 2.0, "AvgGoalsConcededInBox": 28.125, "AvgGoalsConcededOutBox": 1.875, "AvgGoodHighClaim": 21.666666666666668, "AvgKeeperPickUp": 7.766666666666667, "AvgLongPassOwnToOpp": 16.566666666666666, "AvgLongPassOwnToOppSuccess": 0.010462776659959759, "AvgLostCorners": 0.7, "AvgOpenPlayPass": 13.233333333333333, "AvgPenGoalsConceded": null, "AvgPenaltyFaced": 0.03333333333333333, "AvgPenaltySave": null, "AvgPossLostAll": 13.266666666666667, "AvgPossLostCtrl": 13.266666666666667, "AvgPossWonDef3rd": 0.36666666666666664, "AvgSavedInbox": 19.677419354838708, "AvgSavedOutbox": 10.0, "TotalSaves": 93.0, "AvgSaves": 3.1, "AvgStandCatch": 0.23333333333333334, "AvgStandSave": 0.03225806451612903, "AvgTouches": 36.2, "Id": 7548.0, "Team": "Crystal Palace", "TeamId": 6, "Position": "G"}, {"name": "Jordan Pickford", "avgAccBackZonePass": 29.152466367713004, "avgAccChippedPass": 18.17391304347826, "avgAccFwdZonePass": 11.134615384615383, "avgAccGoalKicks": 19.21333333333333, "avgAccSweeper": 33.0, "avgAccTrows": 32.58227848101266, "avgAccLaunches": 9.964285714285715, "AvgAccLongBalls": 12.476190476190476, "AvgAccPasses": 19.028487229862474, "TotalAerials": null, "AvgWonAerials": null, "AvgLostAerials": null, "AvgAttemptsConcededInBox": 21.785515320334262, "AvgAttemptsConcededOutBox": 11.214484679665738, "TotalAttemptsConceded": 359.0, "ChallengeLost": 3.0, "CleanSheets": 8, "OddsCleanSheets": 0.24242424242424243, "DivingSave": 37.0, "EffectiveClearances": 20.0, "AvgEffectiveClearances": null, "GkSmother": 3.0, "AvgGoalsConcededInBox": 27.5, "AvgGoalsConcededOutBox": 5.5, "AvgGoodHighClaim": 29.7, "AvgKeeperPickUp": 8.121212121212121, "AvgLongPassOwnToOpp": 17.363636363636363, "AvgLongPassOwnToOppSuccess": 0.010206779840287694, "AvgLostCorners": 0.5151515151515151, "AvgOpenPlayPass": 17.78787878787879, "AvgPenGoalsConceded": 0.030303030303030304, "AvgPenaltyFaced": 0.030303030303030304, "AvgPenaltySave": null, "AvgPossLostAll": 13.333333333333334, "AvgPossLostCtrl": 13.333333333333334, "AvgPossWonDef3rd": 0.5151515151515151, "AvgSavedInbox": 20.77777777777778, "AvgSavedOutbox": 12.222222222222221, "TotalSaves": 81.0, "AvgSaves": 2.4545454545454546, "AvgStandCatch": 0.21212121212121213, "AvgStandSave": 0.08641975308641975, "AvgTouches": 40.0, "Id": 4640.0, "Team": "Everton", "TeamId": 7, "Position": "G"}, {"name": "Kasper Schmeichel", "avgAccBackZonePass": 30.101024890190338, "avgAccChippedPass": 21.078534031413614, "avgAccFwdZonePass": 8.164948453608247, "avgAccGoalKicks": 27.26760563380282, "avgAccSweeper": 28.875, "avgAccTrows": 32.07042253521127, "avgAccLaunches": 5.783505154639175, "AvgAccLongBalls": 16.786600496277917, "AvgAccPasses": 25.248574686431013, "TotalAerials": 10.0, "AvgWonAerials": 26.400000000000002, "AvgLostAerials": 6.6000000000000005, "AvgAttemptsConcededInBox": 21.61061946902655, "AvgAttemptsConcededOutBox": 11.389380530973451, "TotalAttemptsConceded": 339.0, "BlockedPass": 1.0, "ChallengeLost": 1.0, "CleanSheets": 12, "OddsCleanSheets": 0.36363636363636365, "CrossesNotClaimed": 2.0, "DiveCatches": 1.0, "DivingSave": 38.0, "EffectiveClearances": 10.0, "AvgEffectiveClearances": 39.6, "EffectiveHeadClearance": 2.0, "GkSmother": 4.0, "AvgGoalsConcededInBox": 30.87096774193548, "AvgGoalsConcededOutBox": 2.129032258064516, "AvgGoodHighClaim": 33.0, "AvgKeeperPickUp": 5.484848484848484, "AvgLongPassOwnToOpp": 5.9393939393939394, "AvgLongPassOwnToOppSuccess": 0.007730364873222016, "AvgLostCorners": 0.36363636363636365, "AvgOpenPlayPass": 15.93939393939394, "AvgPenGoalsConceded": 0.18181818181818182, "AvgPenaltyFaced": 0.24242424242424243, "AvgPenaltySave": 0.25, "AvgPossLostAll": 6.575757575757576, "AvgPossLostCtrl": 6.575757575757576, "AvgPossWonDef3rd": 1.0303030303030303, "AvgSavedInbox": 24.174418604651162, "AvgSavedOutbox": 8.825581395348836, "TotalSaves": 86.0, "AvgSaves": 2.606060606060606, "AvgStandCatch": 0.2727272727272727, "AvgStandSave": 0.10465116279069768, "AvgTouches": 34.878787878787875, "Id": 2508.0, "Team": "Leicester", "TeamId": 26, "Position": "G"}, {"name": "Alisson", "avgAccBackZonePass": 22.804270462633454, "avgAccChippedPass": 15.578947368421053, "avgAccFwdZonePass": 8.142857142857142, "avgAccGoalKicks": 19.914893617021278, "avgAccSweeper": 24.0, "avgAccTrows": 23.787610619469028, "avgAccLaunches": 5.5813953488372094, "AvgAccLongBalls": 11.550802139037433, "AvgAccPasses": 20.367952522255194, "TotalAerials": null, "AvgWonAerials": null, "AvgLostAerials": null, "AvgAttemptsConcededInBox": 15.404651162790696, "AvgAttemptsConcededOutBox": 8.595348837209302, "TotalAttemptsConceded": 215.0, "ChallengeLost": 1.0, "CleanSheets": 13, "OddsCleanSheets": 0.5416666666666667, "CrossesNotClaimed": 0.0, "DiveCatches": 2.0, "DivingSave": 20.0, "EffectiveClearances": 15.0, "AvgEffectiveClearances": null, "GkSmother": 4.0, "AvgGoalsConcededInBox": 24.0, "AvgGoalsConcededOutBox": null, "AvgGoodHighClaim": 18.0, "AvgKeeperPickUp": 6.166666666666667, "AvgLongPassOwnToOpp": 4.708333333333333, "AvgLongPassOwnToOppSuccess": 0.014380530973451327, "AvgLostCorners": 0.625, "AvgOpenPlayPass": 19.083333333333332, "AvgPenGoalsConceded": 0.041666666666666664, "AvgPenaltyFaced": 0.041666666666666664, "AvgPenaltySave": null, "AvgPossLostAll": 4.375, "AvgPossLostCtrl": 4.375, "AvgPossWonDef3rd": 1.7916666666666667, "AvgSavedInbox": 13.132075471698112, "AvgSavedOutbox": 10.867924528301888, "TotalSaves": 53.0, "AvgSaves": 2.2083333333333335, "AvgStandCatch": 0.125, "AvgStandSave": 0.05660377358490566, "AvgTouches": 36.291666666666664, "Id": 20559.0, "Team": "Liverpool", "TeamId": 10, "Position": "G"}, {"name": "Adri\u00e1n", "avgAccBackZonePass": 9.618090452261306, "avgAccChippedPass": 6.6, "avgAccFwdZonePass": 2.344262295081967, "avgAccGoalKicks": 9.428571428571429, "avgAccSweeper": 11.0, "avgAccTrows": 11.0, "avgAccLaunches": 2.3404255319148937, "AvgAccLongBalls": 4.545454545454546, "AvgAccPasses": 7.911538461538462, "TotalAerials": null, "AvgWonAerials": null, "AvgLostAerials": null, "AvgAttemptsConcededInBox": 6.860215053763441, "AvgAttemptsConcededOutBox": 4.139784946236559, "TotalAttemptsConceded": 93.0, "BlockedPass": 1.0, "CleanSheets": 2, "OddsCleanSheets": 0.1818181818181818, "CrossesNotClaimed": 0.0, "DivingSave": 6.0, "EffectiveClearances": 12.0, "AvgEffectiveClearances": 11.916666666666666, "EffectiveHeadClearance": 1.0, "GkSmother": 3.0, "AvgGoalsConcededInBox": 8.8, "AvgGoalsConcededOutBox": 2.2, "AvgGoodHighClaim": 7.857142857142858, "AvgKeeperPickUp": 5.7272727272727275, "AvgLongPassOwnToOpp": 5.545454545454546, "AvgLongPassOwnToOppSuccess": 0.019374068554396422, "AvgLostCorners": 0.36363636363636365, "AvgOpenPlayPass": 13.818181818181818, "AvgPenGoalsConceded": null, "AvgPenaltyFaced": null, "AvgPenaltySave": null, "AvgPossLostAll": 6.636363636363637, "AvgPossLostCtrl": 6.636363636363637, "AvgPossWonDef3rd": 0.45454545454545453, "AvgSavedInbox": 4.888888888888888, "AvgSavedOutbox": 5.5, "TotalSaves": 18.0, "AvgSaves": 1.6363636363636365, "AvgStandCatch": 0.09090909090909091, "AvgStandSave": 0.16666666666666666, "AvgTouches": 32.18181818181818, "Id": 4852.0, "Team": "Liverpool", "TeamId": 10, "Position": "G"}, {"name": "Claudio Bravo", "avgAccBackZonePass": 3.608695652173913, "avgAccChippedPass": 2.6666666666666665, "avgAccFwdZonePass": 1.1851851851851851, "avgAccGoalKicks": 3.0, "avgAccSweeper": null, "avgAccTrows": 3.764705882352941, "avgAccLaunches": 0.9230769230769231, "AvgAccLongBalls": 1.8333333333333333, "AvgAccPasses": 3.0588235294117645, "TotalAerials": null, "AvgWonAerials": null, "AvgLostAerials": null, "AvgAttemptsConcededInBox": 2.8333333333333335, "AvgAttemptsConcededOutBox": 1.1666666666666667, "TotalAttemptsConceded": 48.0, "BlockedPass": 0.0, "CleanSheets": 1, "OddsCleanSheets": 0.25, "DivingSave": 5.0, "EffectiveClearances": 3.0, "AvgEffectiveClearances": null, "AvgGoalsConcededInBox": 2.857142857142857, "AvgGoalsConcededOutBox": 1.1428571428571428, "AvgGoodHighClaim": null, "AvgKeeperPickUp": 5.75, "AvgLongPassOwnToOpp": 6.75, "AvgLongPassOwnToOppSuccess": 0.07407407407407407, "AvgLostCorners": 0.25, "AvgOpenPlayPass": 20.25, "AvgPenGoalsConceded": null, "AvgPenaltyFaced": null, "AvgPenaltySave": null, "AvgPossLostAll": 7.25, "AvgPossLostCtrl": 7.25, "AvgPossWonDef3rd": 0.5, "AvgSavedInbox": 1.5, "AvgSavedOutbox": 2.5, "TotalSaves": 8.0, "AvgSaves": 2.0, "AvgStandCatch": 0.25, "AvgStandSave": 0.125, "AvgTouches": 37.25, "Id": 5810.0, "Team": "Man City", "TeamId": 11, "Position": "G"}, {"name": "Ederson", "avgAccBackZonePass": 28.88198757763975, "avgAccChippedPass": 19.09090909090909, "avgAccFwdZonePass": 9.45945945945946, "avgAccGoalKicks": 24.473684210526315, "avgAccSweeper": 26.470588235294116, "avgAccTrows": 29.605263157894736, "avgAccLaunches": 6.122448979591837, "AvgAccLongBalls": 16.108374384236452, "AvgAccPasses": 26.026490066225165, "TotalAerials": 12.0, "AvgWonAerials": 27.5, "AvgLostAerials": 2.5, "AvgAttemptsConcededInBox": 21.386138613861384, "AvgAttemptsConcededOutBox": 8.613861386138613, "TotalAttemptsConceded": 202.0, "ChallengeLost": 3.0, "CleanSheets": 12, "OddsCleanSheets": 0.4, "DiveCatches": 2.0, "DivingSave": 28.0, "EffectiveClearances": 21.0, "AvgEffectiveClearances": 37.142857142857146, "EffectiveHeadClearance": 5.0, "GkSmother": 3.0, "AvgGoalsConcededInBox": 22.22222222222222, "AvgGoalsConcededOutBox": 7.777777777777778, "AvgGoodHighClaim": 27.272727272727273, "AvgKeeperPickUp": 5.233333333333333, "AvgLongPassOwnToOpp": 3.7, "AvgLongPassOwnToOppSuccess": 0.010510510510510511, "AvgLostCorners": 0.4666666666666667, "AvgOpenPlayPass": 19.733333333333334, "AvgPenGoalsConceded": 0.1, "AvgPenaltyFaced": 0.1, "AvgPenaltySave": null, "AvgPossLostAll": 3.533333333333333, "AvgPossLostCtrl": 3.533333333333333, "AvgPossWonDef3rd": 1.3, "AvgSavedInbox": 22.62295081967213, "AvgSavedOutbox": 7.377049180327869, "TotalSaves": 61.0, "AvgSaves": 2.033333333333333, "AvgStandCatch": 0.03333333333333333, "AvgStandSave": 0.04918032786885246, "AvgTouches": 33.93333333333333, "Id": 12707.0, "Team": "Man City", "TeamId": 11, "Position": "G"}, {"name": "David de Gea", "avgAccBackZonePass": 30.244532803180917, "avgAccChippedPass": 18.5625, "avgAccFwdZonePass": 5.92814371257485, "avgAccGoalKicks": 26.84, "avgAccSweeper": 33.0, "avgAccTrows": 32.266666666666666, "avgAccLaunches": 4.1684210526315795, "AvgAccLongBalls": 9.88663967611336, "AvgAccPasses": 24.18358208955224, "TotalAerials": 9.0, "AvgWonAerials": 33.0, "AvgLostAerials": 0.0, "AvgAttemptsConcededInBox": 20.414414414414416, "AvgAttemptsConcededOutBox": 12.585585585585585, "TotalAttemptsConceded": 333.0, "CleanSheets": 10, "OddsCleanSheets": 0.30303030303030304, "DiveCatches": 0.0, "DivingSave": 39.0, "EffectiveClearances": 15.0, "AvgEffectiveClearances": null, "GkSmother": 1.0, "AvgGoalsConcededInBox": 29.0, "AvgGoalsConcededOutBox": 4.0, "AvgGoodHighClaim": 27.5, "AvgKeeperPickUp": 5.090909090909091, "AvgLongPassOwnToOpp": 5.212121212121212, "AvgLongPassOwnToOppSuccess": 0.005990133897110641, "AvgLostCorners": 0.6060606060606061, "AvgOpenPlayPass": 10.696969696969697, "AvgPenGoalsConceded": 0.06060606060606061, "AvgPenaltyFaced": 0.06060606060606061, "AvgPenaltySave": null, "AvgPossLostAll": 5.575757575757576, "AvgPossLostCtrl": 5.575757575757576, "AvgPossWonDef3rd": 0.9393939393939394, "AvgSavedInbox": 19.317073170731707, "AvgSavedOutbox": 13.682926829268292, "TotalSaves": 82.0, "AvgSaves": 2.484848484848485, "AvgStandCatch": 0.30303030303030304, "AvgStandSave": 0.04878048780487805, "AvgTouches": 27.87878787878788, "Id": 4330.0, "Team": "Man Utd", "TeamId": 12, "Position": "G"}, {"name": "Martin Dubravka", "avgAccBackZonePass": 27.634146341463413, "avgAccChippedPass": 15.75, "avgAccFwdZonePass": 12.463054187192117, "avgAccGoalKicks": 15.321428571428571, "avgAccSweeper": 28.875, "avgAccTrows": 32.679611650485434, "avgAccLaunches": 13.102941176470587, "AvgAccLongBalls": 13.075471698113208, "AvgAccPasses": 16.828070175438597, "TotalAerials": null, "AvgWonAerials": null, "AvgLostAerials": null, "AvgAttemptsConcededInBox": 21.176113360323885, "AvgAttemptsConcededOutBox": 11.823886639676113, "TotalAttemptsConceded": 494.0, "BlockedPass": 4.0, "ChallengeLost": 1.0, "CleanSheets": 10, "OddsCleanSheets": 0.30303030303030304, "DiveCatches": 4.0, "DivingSave": 64.0, "EffectiveClearances": 34.0, "AvgEffectiveClearances": null, "GkSmother": 4.0, "AvgGoalsConcededInBox": 28.6, "AvgGoalsConcededOutBox": 4.4, "AvgGoodHighClaim": 33.0, "AvgKeeperPickUp": 6.333333333333333, "AvgLongPassOwnToOpp": 18.727272727272727, "AvgLongPassOwnToOppSuccess": 0.01147396293027361, "AvgLostCorners": 0.7878787878787878, "AvgOpenPlayPass": 10.878787878787879, "AvgPenGoalsConceded": null, "AvgPenaltyFaced": null, "AvgPenaltySave": null, "AvgPossLostAll": 13.06060606060606, "AvgPossLostCtrl": 13.06060606060606, "AvgPossWonDef3rd": 1.0303030303030303, "AvgSavedInbox": 22.62096774193548, "AvgSavedOutbox": 10.112903225806452, "TotalSaves": 124.0, "AvgSaves": 3.757575757575758, "AvgStandCatch": 0.15151515151515152, "AvgStandSave": 0.024193548387096774, "AvgTouches": 35.27272727272727, "Id": 6451.0, "Team": "Newcastle", "TeamId": 23, "Position": "G"}, {"name": "Tim Krul", "avgAccBackZonePass": 26.143051771117165, "avgAccChippedPass": 13.961832061068701, "avgAccFwdZonePass": 7.28960396039604, "avgAccGoalKicks": 22.43579766536965, "avgAccSweeper": 24.11111111111111, "avgAccTrows": 31.0, "avgAccLaunches": 6.842809364548494, "AvgAccLongBalls": 10.011475409836065, "AvgAccPasses": 19.449912126537786, "TotalAerials": 17.0, "AvgWonAerials": 29.176470588235293, "AvgLostAerials": 1.8235294117647058, "AvgAttemptsConcededInBox": 20.335470085470085, "AvgAttemptsConcededOutBox": 10.664529914529915, "TotalAttemptsConceded": 468.0, "BlockedPass": 3.0, "ChallengeLost": 1.0, "CleanSheets": 5, "OddsCleanSheets": 0.16129032258064518, "CrossesNotClaimed": 0.0, "DivingSave": 53.0, "EffectiveClearances": 29.0, "AvgEffectiveClearances": null, "GkSmother": 1.0, "AvgGoalsConcededInBox": 27.555555555555554, "AvgGoalsConcededOutBox": 3.444444444444444, "AvgGoodHighClaim": 29.85185185185185, "AvgKeeperPickUp": 6.774193548387097, "AvgLongPassOwnToOpp": 13.03225806451613, "AvgLongPassOwnToOppSuccess": 0.0075854359629511335, "AvgLostCorners": 1.0, "AvgOpenPlayPass": 23.677419354838708, "AvgPenGoalsConceded": 0.0967741935483871, "AvgPenaltyFaced": 0.16129032258064516, "AvgPenaltySave": 0.4, "AvgPossLostAll": 13.806451612903226, "AvgPossLostCtrl": 13.806451612903226, "AvgPossWonDef3rd": 0.7419354838709677, "AvgSavedInbox": 19.54954954954955, "AvgSavedOutbox": 10.891891891891893, "TotalSaves": 111.0, "AvgSaves": 3.5806451612903225, "AvgStandCatch": 0.0967741935483871, "AvgStandSave": 0.05405405405405406, "AvgTouches": 48.16129032258065, "Id": 3169.0, "Team": "Norwich", "TeamId": 14, "Position": "G"}, {"name": "Michael McGovern", "avgAccBackZonePass": 1.391304347826087, "avgAccChippedPass": 0.6666666666666666, "avgAccFwdZonePass": 0.35294117647058826, "avgAccGoalKicks": 1.2857142857142858, "avgAccSweeper": 2.0, "avgAccTrows": 2.0, "avgAccLaunches": 0.26666666666666666, "AvgAccLongBalls": 0.32, "AvgAccPasses": 0.95, "TotalAerials": null, "AvgWonAerials": null, "AvgLostAerials": null, "AvgAttemptsConcededInBox": 1.25, "AvgAttemptsConcededOutBox": 0.75, "TotalAttemptsConceded": 32.0, "CleanSheets": 0, "OddsCleanSheets": 0.0, "DivingSave": 4.0, "EffectiveClearances": 3.0, "AvgEffectiveClearances": null, "AvgGoalsConcededInBox": 1.3333333333333333, "AvgGoalsConcededOutBox": 0.6666666666666666, "AvgGoodHighClaim": null, "AvgKeeperPickUp": 6.0, "AvgLongPassOwnToOpp": 8.5, "AvgLongPassOwnToOppSuccess": 0.08823529411764706, "AvgLostCorners": 1.5, "AvgOpenPlayPass": 10.0, "AvgPenGoalsConceded": null, "AvgPenaltyFaced": 0.5, "AvgPenaltySave": 1.0, "AvgPossLostAll": 10.5, "AvgPossLostCtrl": 10.5, "AvgPossWonDef3rd": 1.5, "AvgSavedInbox": 1.1428571428571428, "AvgSavedOutbox": 0.8571428571428571, "TotalSaves": 7.0, "AvgSaves": 3.5, "AvgStandCatch": null, "AvgStandSave": null, "AvgTouches": 30.5, "Id": 19675.0, "Team": "Norwich", "TeamId": 14, "Position": "G"}, {"name": "Ralf F\u00e4hrmann", "avgAccBackZonePass": 0.625, "avgAccChippedPass": null, "avgAccFwdZonePass": null, "avgAccGoalKicks": 1.0, "avgAccSweeper": null, "avgAccTrows": 1.0, "avgAccLaunches": null, "AvgAccLongBalls": null, "AvgAccPasses": 0.625, "TotalAerials": null, "AvgWonAerials": null, "AvgLostAerials": null, "AvgAttemptsConcededInBox": 0.8, "AvgAttemptsConcededOutBox": 0.2, "TotalAttemptsConceded": 5.0, "CleanSheets": 0, "OddsCleanSheets": 0.0, "DivingSave": 1.0, "AvgEffectiveClearances": null, "AvgGoalsConcededInBox": 1.0, "AvgGoalsConcededOutBox": null, "AvgGoodHighClaim": 1.0, "AvgKeeperPickUp": 1.0, "AvgLongPassOwnToOpp": null, "AvgLongPassOwnToOppSuccess": null, "AvgLostCorners": null, "AvgOpenPlayPass": 5.0, "AvgPenGoalsConceded": 1.0, "AvgPenaltyFaced": 1.0, "AvgPenaltySave": null, "AvgPossLostAll": 3.0, "AvgPossLostCtrl": 3.0, "AvgPossWonDef3rd": 2.0, "AvgSavedInbox": null, "AvgSavedOutbox": 1.0, "TotalSaves": 1.0, "AvgSaves": 1.0, "AvgStandCatch": null, "AvgStandSave": null, "AvgTouches": 12.0, "Id": 5361.0, "Team": "Norwich", "TeamId": 14, "Position": "G"}, {"name": "Simon Moore", "avgAccBackZonePass": 1.25, "avgAccChippedPass": 0.6666666666666666, "avgAccFwdZonePass": 0.5555555555555556, "avgAccGoalKicks": 0.7272727272727273, "avgAccSweeper": null, "avgAccTrows": 2.0, "avgAccLaunches": 0.4444444444444444, "AvgAccLongBalls": 0.5128205128205128, "AvgAccPasses": 0.6818181818181818, "TotalAerials": null, "AvgWonAerials": null, "AvgLostAerials": null, "AvgAttemptsConcededInBox": 1.3846153846153846, "AvgAttemptsConcededOutBox": 0.6153846153846154, "TotalAttemptsConceded": 26.0, "ChallengeLost": 0.0, "CleanSheets": 0, "OddsCleanSheets": 0.0, "DivingSave": 1.0, "EffectiveClearances": 0.0, "AvgEffectiveClearances": null, "GkSmother": 2.0, "AvgGoalsConcededInBox": 2.0, "AvgGoalsConcededOutBox": null, "AvgGoodHighClaim": null, "AvgKeeperPickUp": 7.0, "AvgLongPassOwnToOpp": 18.0, "AvgLongPassOwnToOppSuccess": 0.1388888888888889, "AvgLostCorners": 1.0, "AvgOpenPlayPass": 7.0, "AvgPenGoalsConceded": null, "AvgPenaltyFaced": null, "AvgPenaltySave": null, "AvgPossLostAll": 14.5, "AvgPossLostCtrl": 14.5, "AvgPossWonDef3rd": null, "AvgSavedInbox": 0.8, "AvgSavedOutbox": 1.2, "TotalSaves": 5.0, "AvgSaves": 2.5, "AvgStandCatch": null, "AvgStandSave": 0.2, "AvgTouches": 28.0, "Id": 4727.0, "Team": "Sheffield Utd", "TeamId": 18, "Position": "G"}, {"name": "Dean Henderson", "avgAccBackZonePass": 21.94890510948905, "avgAccChippedPass": 13.21311475409836, "avgAccFwdZonePass": 9.290801186943622, "avgAccGoalKicks": 11.357758620689655, "avgAccSweeper": 31.0, "avgAccTrows": 31.0, "avgAccLaunches": 7.901960784313725, "AvgAccLongBalls": 9.6221322537112, "AvgAccPasses": 11.429099876695437, "TotalAerials": null, "AvgWonAerials": null, "AvgLostAerials": null, "AvgAttemptsConcededInBox": 18.900284900284902, "AvgAttemptsConcededOutBox": 12.0997150997151, "TotalAttemptsConceded": 351.0, "CleanSheets": 11, "OddsCleanSheets": 0.3548387096774194, "DivingSave": 47.0, "EffectiveClearances": 23.0, "AvgEffectiveClearances": 33.69565217391304, "EffectiveHeadClearance": 2.0, "GkSmother": 3.0, "AvgGoalsConcededInBox": 28.703703703703702, "AvgGoalsConcededOutBox": 2.2962962962962963, "AvgGoodHighClaim": 23.705882352941174, "AvgKeeperPickUp": 7.838709677419355, "AvgLongPassOwnToOpp": 21.741935483870968, "AvgLongPassOwnToOppSuccess": 0.009667847228869533, "AvgLostCorners": 0.6129032258064516, "AvgOpenPlayPass": 12.161290322580646, "AvgPenGoalsConceded": null, "AvgPenaltyFaced": 0.06451612903225806, "AvgPenaltySave": 0.5, "AvgPossLostAll": 16.70967741935484, "AvgPossLostCtrl": 16.70967741935484, "AvgPossWonDef3rd": 0.5483870967741935, "AvgSavedInbox": 18.96470588235294, "AvgSavedOutbox": 11.305882352941175, "TotalSaves": 85.0, "AvgSaves": 2.7419354838709675, "AvgStandCatch": 0.1935483870967742, "AvgStandSave": 0.023529411764705882, "AvgTouches": 33.83870967741935, "Id": 13988.0, "Team": "Sheffield Utd", "TeamId": 18, "Position": "G"}, {"name": "Alex McCarthy", "avgAccBackZonePass": 18.71186440677966, "avgAccChippedPass": 9.200000000000001, "avgAccFwdZonePass": 7.842239185750636, "avgAccGoalKicks": 10.397260273972602, "avgAccSweeper": 23.0, "avgAccTrows": 23.0, "avgAccLaunches": 8.363636363636363, "AvgAccLongBalls": 8.460352422907489, "AvgAccPasses": 11.217543859649123, "TotalAerials": 15.0, "AvgWonAerials": 19.933333333333334, "AvgLostAerials": 3.0666666666666664, "AvgAttemptsConcededInBox": 15.833333333333332, "AvgAttemptsConcededOutBox": 7.166666666666667, "TotalAttemptsConceded": 276.0, "BlockedPass": 1.0, "CleanSheets": 6, "OddsCleanSheets": 0.2608695652173913, "CrossesNotClaimed": 1.0, "DiveCatches": 2.0, "DivingSave": 36.0, "EffectiveClearances": 19.0, "AvgEffectiveClearances": 23.0, "EffectiveHeadClearance": 0.0, "GkSmother": 2.0, "AvgGoalsConcededInBox": 20.7, "AvgGoalsConcededOutBox": 2.3000000000000003, "AvgGoodHighClaim": 19.71428571428571, "AvgKeeperPickUp": 6.086956521739131, "AvgLongPassOwnToOpp": 17.08695652173913, "AvgLongPassOwnToOppSuccess": 0.014824648744330125, "AvgLostCorners": 0.9565217391304348, "AvgOpenPlayPass": 11.434782608695652, "AvgPenGoalsConceded": 0.043478260869565216, "AvgPenaltyFaced": 0.08695652173913043, "AvgPenaltySave": 0.5, "AvgPossLostAll": 12.91304347826087, "AvgPossLostCtrl": 12.91304347826087, "AvgPossWonDef3rd": 1.0434782608695652, "AvgSavedInbox": 16.573529411764707, "AvgSavedOutbox": 6.426470588235294, "TotalSaves": 68.0, "AvgSaves": 2.9565217391304346, "AvgStandCatch": 0.13043478260869565, "AvgStandSave": 0.08823529411764706, "AvgTouches": 32.56521739130435, "Id": 4573.0, "Team": "Southampton", "TeamId": 20, "Position": "G"}, {"name": "Angus Gunn", "avgAccBackZonePass": 7.733333333333333, "avgAccChippedPass": 6.111111111111112, "avgAccFwdZonePass": 1.858974358974359, "avgAccGoalKicks": 2.987012987012987, "avgAccSweeper": 8.333333333333334, "avgAccTrows": 10.0, "avgAccLaunches": 1.4634146341463414, "AvgAccLongBalls": 2.299465240641711, "AvgAccPasses": 3.7662337662337664, "TotalAerials": null, "AvgWonAerials": null, "AvgLostAerials": null, "AvgAttemptsConcededInBox": 6.515151515151515, "AvgAttemptsConcededOutBox": 3.4848484848484853, "TotalAttemptsConceded": 132.0, "ChallengeLost": 2.0, "CleanSheets": 2, "OddsCleanSheets": 0.2, "DivingSave": 15.0, "EffectiveClearances": 3.0, "AvgEffectiveClearances": null, "GkSmother": 1.0, "AvgGoalsConcededInBox": 9.200000000000001, "AvgGoalsConcededOutBox": 0.8, "AvgGoodHighClaim": 7.5, "AvgKeeperPickUp": 5.6, "AvgLongPassOwnToOpp": 15.6, "AvgLongPassOwnToOppSuccess": 0.01858974358974359, "AvgLostCorners": 0.6, "AvgOpenPlayPass": 9.8, "AvgPenGoalsConceded": 0.2, "AvgPenaltyFaced": 0.2, "AvgPenaltySave": null, "AvgPossLostAll": 14.4, "AvgPossLostCtrl": 14.4, "AvgPossWonDef3rd": 0.9, "AvgSavedInbox": 6.666666666666666, "AvgSavedOutbox": 3.333333333333333, "TotalSaves": 30.0, "AvgSaves": 3.0, "AvgStandCatch": 0.2, "AvgStandSave": 0.1, "AvgTouches": 29.9, "Id": 15269.0, "Team": "Southampton", "TeamId": 20, "Position": "G"}, {"name": "Hugo Lloris", "avgAccBackZonePass": 14.137931034482758, "avgAccChippedPass": 9.0, "avgAccFwdZonePass": 4.8, "avgAccGoalKicks": 13.064220183486238, "avgAccSweeper": 16.0, "avgAccTrows": 16.0, "avgAccLaunches": 3.5555555555555554, "AvgAccLongBalls": 6.6878306878306875, "AvgAccPasses": 10.954545454545455, "TotalAerials": 7.0, "AvgWonAerials": 11.428571428571429, "AvgLostAerials": 4.571428571428571, "AvgAttemptsConcededInBox": 10.175115207373272, "AvgAttemptsConcededOutBox": 5.824884792626728, "TotalAttemptsConceded": 217.0, "CleanSheets": 3, "OddsCleanSheets": 0.1875, "DiveCatches": 1.0, "DivingSave": 34.0, "EffectiveClearances": 11.0, "AvgEffectiveClearances": null, "GkSmother": 2.0, "AvgGoalsConcededInBox": 15.11111111111111, "AvgGoalsConcededOutBox": 0.8888888888888888, "AvgGoodHighClaim": 12.444444444444445, "AvgKeeperPickUp": 6.8125, "AvgLongPassOwnToOpp": 7.5, "AvgLongPassOwnToOppSuccess": 0.01875, "AvgLostCorners": 0.875, "AvgOpenPlayPass": 12.1875, "AvgPenGoalsConceded": 0.125, "AvgPenaltyFaced": 0.1875, "AvgPenaltySave": 0.3333333333333333, "AvgPossLostAll": 7.125, "AvgPossLostCtrl": 7.125, "AvgPossWonDef3rd": 0.75, "AvgSavedInbox": 8.918032786885245, "AvgSavedOutbox": 6.557377049180328, "TotalSaves": 61.0, "AvgSaves": 3.8125, "AvgStandCatch": null, "AvgStandSave": 0.04918032786885246, "AvgTouches": 32.375, "Id": 4664.0, "Team": "Spurs", "TeamId": 21, "Position": "G"}, {"name": "Paulo Gazzaniga", "avgAccBackZonePass": 15.776892430278885, "avgAccChippedPass": 11.5, "avgAccFwdZonePass": 4.478048780487805, "avgAccGoalKicks": 9.760563380281692, "avgAccSweeper": 18.0, "avgAccTrows": 18.0, "avgAccLaunches": 4.168421052631579, "AvgAccLongBalls": 5.2615384615384615, "AvgAccPasses": 10.697368421052632, "TotalAerials": 6.0, "AvgWonAerials": 15.0, "AvgLostAerials": 3.0, "AvgAttemptsConcededInBox": 11.53846153846154, "AvgAttemptsConcededOutBox": 6.461538461538462, "TotalAttemptsConceded": 234.0, "CleanSheets": 2, "OddsCleanSheets": 0.1111111111111111, "DivingSave": 34.0, "EffectiveClearances": 7.0, "AvgEffectiveClearances": 20.57142857142857, "EffectiveHeadClearance": 1.0, "GkSmother": 3.0, "AvgGoalsConcededInBox": 15.23076923076923, "AvgGoalsConcededOutBox": 2.769230769230769, "AvgGoodHighClaim": 18.0, "AvgKeeperPickUp": 5.833333333333333, "AvgLongPassOwnToOpp": 10.88888888888889, "AvgLongPassOwnToOppSuccess": 0.013605442176870748, "AvgLostCorners": 0.6111111111111112, "AvgOpenPlayPass": 13.833333333333334, "AvgPenGoalsConceded": 0.16666666666666666, "AvgPenaltyFaced": 0.2222222222222222, "AvgPenaltySave": 0.25, "AvgPossLostAll": 10.444444444444445, "AvgPossLostCtrl": 10.444444444444445, "AvgPossWonDef3rd": 0.8888888888888888, "AvgSavedInbox": 10.983050847457628, "AvgSavedOutbox": 6.406779661016949, "TotalSaves": 59.0, "AvgSaves": 3.2777777777777777, "AvgStandCatch": 0.3888888888888889, "AvgStandSave": 0.1016949152542373, "AvgTouches": 33.5, "Id": 4600.0, "Team": "Spurs", "TeamId": 21, "Position": "G"}, {"name": "Ben Foster", "avgAccBackZonePass": 25.18421052631579, "avgAccChippedPass": 20.30769230769231, "avgAccFwdZonePass": 10.153846153846155, "avgAccGoalKicks": 11.965648854961831, "avgAccSweeper": 31.166666666666664, "avgAccTrows": 31.058823529411764, "avgAccLaunches": 9.796875, "AvgAccLongBalls": 10.847750865051903, "AvgAccPasses": 13.097938144329897, "TotalAerials": null, "AvgWonAerials": null, "AvgLostAerials": null, "AvgAttemptsConcededInBox": 20.951162790697676, "AvgAttemptsConcededOutBox": 12.048837209302325, "TotalAttemptsConceded": 430.0, "BlockedPass": 1.0, "ChallengeLost": 2.0, "CleanSheets": 9, "OddsCleanSheets": 0.2727272727272727, "DiveCatches": 1.0, "DivingSave": 45.0, "EffectiveClearances": 25.0, "AvgEffectiveClearances": 34.32, "EffectiveHeadClearance": 1.0, "GkSmother": 4.0, "AvgGoalsConcededInBox": 29.19230769230769, "AvgGoalsConcededOutBox": 3.807692307692308, "AvgGoodHighClaim": 26.125, "AvgKeeperPickUp": 7.96969696969697, "AvgLongPassOwnToOpp": 23.696969696969695, "AvgLongPassOwnToOppSuccess": 0.00937766410912191, "AvgLostCorners": 0.5454545454545454, "AvgOpenPlayPass": 14.0, "AvgPenGoalsConceded": 0.21212121212121213, "AvgPenaltyFaced": 0.21212121212121213, "AvgPenaltySave": null, "AvgPossLostAll": 18.272727272727273, "AvgPossLostCtrl": 18.272727272727273, "AvgPossWonDef3rd": 1.4545454545454546, "AvgSavedInbox": 23.70873786407767, "AvgSavedOutbox": 9.291262135922329, "TotalSaves": 103.0, "AvgSaves": 3.121212121212121, "AvgStandCatch": 0.2727272727272727, "AvgStandSave": 0.04854368932038835, "AvgTouches": 38.09090909090909, "Id": 2932.0, "Team": "Watford", "TeamId": 33, "Position": "G"}, {"name": "Lukasz Fabianski", "avgAccBackZonePass": 14.796747967479675, "avgAccChippedPass": 8.0, "avgAccFwdZonePass": 7.852760736196319, "avgAccGoalKicks": 10.46979865771812, "avgAccSweeper": 20.0, "avgAccTrows": 18.96103896103896, "avgAccLaunches": 6.758620689655173, "AvgAccLongBalls": 8.238341968911918, "AvgAccPasses": 9.755011135857462, "TotalAerials": null, "AvgWonAerials": null, "AvgLostAerials": null, "AvgAttemptsConcededInBox": 13.360000000000001, "AvgAttemptsConcededOutBox": 6.640000000000001, "TotalAttemptsConceded": 250.0, "BlockedPass": 2.0, "ChallengeLost": 2.0, "CleanSheets": 4, "OddsCleanSheets": 0.2, "DiveCatches": 2.0, "DivingSave": 29.0, "EffectiveClearances": 18.0, "AvgEffectiveClearances": null, "GkSmother": 7.0, "AvgGoalsConcededInBox": 18.0, "AvgGoalsConcededOutBox": 2.0, "AvgGoodHighClaim": 18.0, "AvgKeeperPickUp": 7.0, "AvgLongPassOwnToOpp": 16.55, "AvgLongPassOwnToOppSuccess": 0.019637462235649546, "AvgLostCorners": 0.55, "AvgOpenPlayPass": 10.1, "AvgPenGoalsConceded": 0.15, "AvgPenaltyFaced": 0.2, "AvgPenaltySave": 0.25, "AvgPossLostAll": 12.05, "AvgPossLostCtrl": 12.05, "AvgPossWonDef3rd": 0.4, "AvgSavedInbox": 11.864406779661017, "AvgSavedOutbox": 8.135593220338983, "TotalSaves": 59.0, "AvgSaves": 2.95, "AvgStandCatch": 0.15, "AvgStandSave": 0.05084745762711865, "AvgTouches": 31.65, "Id": 3309.0, "Team": "West Ham", "TeamId": 25, "Position": "G"}, {"name": "David Martin", "avgAccBackZonePass": 3.0, "avgAccChippedPass": null, "avgAccFwdZonePass": 1.8131868131868132, "avgAccGoalKicks": 2.2727272727272725, "avgAccSweeper": null, "avgAccTrows": 4.583333333333333, "avgAccLaunches": 1.5555555555555556, "AvgAccLongBalls": 1.9047619047619047, "AvgAccPasses": 2.027027027027027, "TotalAerials": 2.0, "AvgWonAerials": 2.5, "AvgLostAerials": 2.5, "AvgAttemptsConcededInBox": 3.6923076923076925, "AvgAttemptsConcededOutBox": 1.3076923076923077, "TotalAttemptsConceded": 65.0, "CleanSheets": 2, "OddsCleanSheets": 0.4, "DivingSave": 4.0, "EffectiveClearances": 2.0, "AvgEffectiveClearances": null, "GkSmother": 1.0, "AvgGoalsConcededInBox": 5.0, "AvgGoalsConcededOutBox": null, "AvgGoodHighClaim": 5.0, "AvgKeeperPickUp": 5.4, "AvgLongPassOwnToOpp": 18.2, "AvgLongPassOwnToOppSuccess": 0.07252747252747252, "AvgLostCorners": 0.4, "AvgOpenPlayPass": 7.2, "AvgPenGoalsConceded": null, "AvgPenaltyFaced": null, "AvgPenaltySave": null, "AvgPossLostAll": 13.6, "AvgPossLostCtrl": 13.6, "AvgPossWonDef3rd": 0.6, "AvgSavedInbox": 4.0, "AvgSavedOutbox": 1.0, "TotalSaves": 15.0, "AvgSaves": 3.0, "AvgStandCatch": null, "AvgStandSave": null, "AvgTouches": 28.6, "Id": 2912.0, "Team": "West Ham", "TeamId": 25, "Position": "G"}, {"name": "Darren Randolph", "avgAccBackZonePass": 1.1666666666666667, "avgAccChippedPass": null, "avgAccFwdZonePass": 0.9166666666666666, "avgAccGoalKicks": 1.2857142857142858, "avgAccSweeper": 2.0, "avgAccTrows": 2.0, "avgAccLaunches": 0.7272727272727273, "AvgAccLongBalls": 0.9411764705882353, "AvgAccPasses": 1.0, "TotalAerials": null, "AvgWonAerials": null, "AvgLostAerials": null, "AvgAttemptsConcededInBox": 1.4, "AvgAttemptsConcededOutBox": 0.6, "TotalAttemptsConceded": 30.0, "CleanSheets": 0, "OddsCleanSheets": 0.0, "DivingSave": 3.0, "EffectiveClearances": 2.0, "AvgEffectiveClearances": null, "GkSmother": 1.0, "AvgGoalsConcededInBox": 2.0, "AvgGoalsConcededOutBox": null, "AvgGoodHighClaim": null, "AvgKeeperPickUp": 5.5, "AvgLongPassOwnToOpp": 12.0, "AvgLongPassOwnToOppSuccess": 0.22916666666666666, "AvgLostCorners": 1.0, "AvgOpenPlayPass": 5.5, "AvgPenGoalsConceded": 0.5, "AvgPenaltyFaced": 0.5, "AvgPenaltySave": null, "AvgPossLostAll": 9.5, "AvgPossLostCtrl": 9.5, "AvgPossWonDef3rd": 0.5, "AvgSavedInbox": 1.6666666666666667, "AvgSavedOutbox": 0.3333333333333333, "TotalSaves": 6.0, "AvgSaves": 3.0, "AvgStandCatch": null, "AvgStandSave": null, "AvgTouches": 25.5, "Id": 2216.0, "Team": "West Ham", "TeamId": 25, "Position": "G"}, {"name": "Rui Patr\u00edcio", "avgAccBackZonePass": 25.36436170212766, "avgAccChippedPass": 26.31645569620253, "avgAccFwdZonePass": 12.6328125, "avgAccGoalKicks": 20.277108433734938, "avgAccSweeper": 33.0, "avgAccTrows": 32.71052631578947, "avgAccLaunches": 11.9625, "AvgAccLongBalls": 16.43125, "AvgAccPasses": 20.20727848101266, "TotalAerials": 10.0, "AvgWonAerials": 29.7, "AvgLostAerials": 3.3000000000000003, "AvgAttemptsConcededInBox": 20.808333333333334, "AvgAttemptsConcededOutBox": 12.191666666666666, "TotalAttemptsConceded": 360.0, "BlockedPass": 2.0, "ChallengeLost": 1.0, "CleanSheets": 11, "OddsCleanSheets": 0.3333333333333333, "CrossesNotClaimed": 0.0, "DiveCatches": 1.0, "DivingSave": 37.0, "EffectiveClearances": 10.0, "AvgEffectiveClearances": 36.300000000000004, "EffectiveHeadClearance": 1.0, "GkSmother": 2.0, "AvgGoalsConcededInBox": 31.166666666666664, "AvgGoalsConcededOutBox": 1.8333333333333333, "AvgGoodHighClaim": 31.058823529411764, "AvgKeeperPickUp": 6.484848484848484, "AvgLongPassOwnToOpp": 7.787878787878788, "AvgLongPassOwnToOppSuccess": 0.011673151750972763, "AvgLostCorners": 0.3939393939393939, "AvgOpenPlayPass": 8.393939393939394, "AvgPenGoalsConceded": null, "AvgPenaltyFaced": 0.06060606060606061, "AvgPenaltySave": 1.0, "AvgPossLostAll": 7.545454545454546, "AvgPossLostCtrl": 7.545454545454546, "AvgPossWonDef3rd": 0.9090909090909091, "AvgSavedInbox": 23.060240963855424, "AvgSavedOutbox": 9.542168674698795, "TotalSaves": 83.0, "AvgSaves": 2.515151515151515, "AvgStandCatch": 0.15151515151515152, "AvgStandSave": 0.060240963855421686, "AvgTouches": 26.454545454545453, "Id": 11341.0, "Team": "Wolves", "TeamId": 38, "Position": "G"}]