{
    "12": [
        {
            "label": "2019/20",
            "id": 276.0
        },
        {
            "label": "2018/19",
            "id": 211.0
        },
        {
            "label": "2017/18",
            "id": 83.0
        },
        {
            "label": "2016/17",
            "id": 55.0
        },
        {
            "label": "2014/15",
            "id": 264.0
        },
        {
            "label": "2013/14",
            "id": 105.0
        },
        {
            "label": "2012/13",
            "id": 104.0
        },
        {
            "label": "2011/12",
            "id": 103.0
        },
        {
            "label": "2010/11",
            "id": 109.0
        },
        {
            "label": "2009/10",
            "id": 108.0
        },
        {
            "label": "1996/97",
            "id": 73.0
        }
    ]
}